tsbenchmarks/__init__.py
tsbenchmarks/_nbdev.py
tsbenchmarks/core.py
tsbenchmarks-0.0.2.dist-info/LICENSE
tsbenchmarks-0.0.2.dist-info/METADATA
tsbenchmarks-0.0.2.dist-info/WHEEL
tsbenchmarks-0.0.2.dist-info/entry_points.txt
tsbenchmarks-0.0.2.dist-info/top_level.txt
tsbenchmarks-0.0.2.dist-info/RECORD
