Metadata-Version: 2.1
Name: tsbenchmarks
Version: 0.0.2
Summary: Time series forecasting benchmarking
Home-page: https://github.com/Nixtla/tsbenchmarks/tree/master/
Author: Nixtla and contributors
Author-email: fede.garza.ramirez@gmail.com
License: MIT License
Keywords: time series,benchmarking,benchmark,M4,M5,forecasting
Platform: UNKNOWN
Classifier: Development Status :: 3 - Alpha
Classifier: Intended Audience :: Developers
Classifier: Natural Language :: English
Classifier: Programming Language :: Python :: 3.7
Classifier: Programming Language :: Python :: 3.8
Classifier: License :: OSI Approved :: MIT License
Requires-Python: >=3.7
Requires-Dist: pip
Requires-Dist: packaging
Requires-Dist: pandas
Requires-Dist: numpy
Requires-Dist: pyarrow
Requires-Dist: python-dotenv
Requires-Dist: requests
Requires-Dist: s3fs
Requires-Dist: boto3
Requires-Dist: tqdm
Provides-Extra: dev
